microacme.py
microacme-3.2.4.dist-info/DESCRIPTION.rst
microacme-3.2.4.dist-info/METADATA
microacme-3.2.4.dist-info/RECORD
microacme-3.2.4.dist-info/WHEEL
microacme-3.2.4.dist-info/metadata.json
microacme-3.2.4.dist-info/top_level.txt
microacme-3.2.4.dist-info/zip-safe
