Metadata-Version: 2.0
Name: microacme
Version: 3.2.4
Summary: UNKNOWN
Home-page: https://gitlab.mirus.io/domains/roadrunner/microacme/
Author: Don Spaulding II
Author-email: don@mirusresearch.com
License: UNKNOWN
Platform: UNKNOWN
Requires-Dist: requests
Requires-Dist: jwcrypto
Requires-Dist: cryptography
Requires-Dist: pytest
Requires-Dist: pytest-cov
